MANIFEST.in
README.rst
setup.py
gpiodaemon/__init__.py
gpiodaemon/__main__.py
gpiodaemon/gpiodaemon.py
gpiodaemon.egg-info/PKG-INFO
gpiodaemon.egg-info/SOURCES.txt
gpiodaemon.egg-info/dependency_links.txt
gpiodaemon.egg-info/entry_points.txt
gpiodaemon.egg-info/requires.txt
gpiodaemon.egg-info/top_level.txt
gpiodaemon.egg-info/zip-safe
systemd/gpiodaemon.service